easyfunc/__init__.py
easyfunc/easyfunc.py
easyfunc/test_easyfunc.py
easyfunc-0.2.5.1.dist-info/LICENSE
easyfunc-0.2.5.1.dist-info/METADATA
easyfunc-0.2.5.1.dist-info/WHEEL
easyfunc-0.2.5.1.dist-info/top_level.txt
easyfunc-0.2.5.1.dist-info/RECORD
