Metadata-Version: 2.1
Name: easyfunc
Version: 0.2.5.1
Summary: Easy and simple functional programming style helper for python
Home-page: https://github.com/DiamondGo/easyfunc
Author: K
Author-email: mastercoderk@gmail.com
License: UNKNOWN
Keywords: fp,python,functional
Platform: UNKNOWN
Classifier: Programming Language :: Python :: 2.6
Classifier: Programming Language :: Python :: 2.7
Classifier: Programming Language :: Python :: 3
Classifier: License :: OSI Approved :: GNU General Public License v2 (GPLv2)
Classifier: Operating System :: OS Independent
License-File: LICENSE
